nonebot_bison-0.9.14.dist-info/METADATA
nonebot_bison-0.9.14.dist-info/WHEEL
nonebot_bison-0.9.14.dist-info/entry_points.txt
nonebot_bison-0.9.14.dist-info/licenses/LICENSE
nonebot_bison/__init__.py
nonebot_bison/admin_page/__init__.py
nonebot_bison/admin_page/api.py
nonebot_bison/admin_page/dist/.gitkeep
nonebot_bison/admin_page/dist/asset-manifest.json
nonebot_bison/admin_page/dist/favicon.ico
nonebot_bison/admin_page/dist/index.html
nonebot_bison/admin_page/dist/logo192.png
nonebot_bison/admin_page/dist/logo512.png
nonebot_bison/admin_page/dist/manifest.json
nonebot_bison/admin_page/dist/robots.txt
nonebot_bison/admin_page/dist/static/css/main.b3143903.css
nonebot_bison/admin_page/dist/static/css/main.b3143903.css.map
nonebot_bison/admin_page/dist/static/js/329.a5d46f84.chunk.js
nonebot_bison/admin_page/dist/static/js/329.a5d46f84.chunk.js.map
nonebot_bison/admin_page/dist/static/js/main.c1efcb31.js
nonebot_bison/admin_page/dist/static/js/main.c1efcb31.js.LICENSE.txt
nonebot_bison/admin_page/dist/static/js/main.c1efcb31.js.map
nonebot_bison/admin_page/jwt.py
nonebot_bison/admin_page/token_manager.py
nonebot_bison/admin_page/types.py
nonebot_bison/apis.py
nonebot_bison/bootstrap.py
nonebot_bison/compat.py
nonebot_bison/config/__init__.py
nonebot_bison/config/config_legacy.py
nonebot_bison/config/db_config.py
nonebot_bison/config/db_migration.py
nonebot_bison/config/db_model.py
nonebot_bison/config/migrations/0571870f5222_init_db.py
nonebot_bison/config/migrations/4a46ba54a3f3_alter_type.py
nonebot_bison/config/migrations/5da28f6facb3_rename_tables.py
nonebot_bison/config/migrations/5f3370328e44_add_time_weight_table.py
nonebot_bison/config/migrations/632b8086bc2b_add_user_target.py
nonebot_bison/config/migrations/67c38b3f39c2_make_user_target_not_nullable.py
nonebot_bison/config/migrations/8d3863e9d74b_remove_uid_and_type.py
nonebot_bison/config/migrations/a333d6224193_add_last_scheduled_time.py
nonebot_bison/config/migrations/a5466912fad0_map_user.py
nonebot_bison/config/migrations/aceef470d69c_alter_fields_not_null.py
nonebot_bison/config/migrations/bd92923c218f_alter_json_not_null.py
nonebot_bison-0.9.14.dist-info/RECORD
