Metadata-Version: 2.1
Name: nonebot-bison
Version: 0.9.14
Summary: Subscribe message from social medias
Keywords: nonebot,nonebot2,qqbot
Author-Email: felinae98 <felinae225@qq.com>
License: MIT
Classifier: Development Status :: 4 - Beta
Classifier: Operating System :: POSIX :: Linux
Classifier: Operating System :: Microsoft :: Windows
Classifier: Operating System :: MacOS
Classifier: Programming Language :: Python :: 3.10
Classifier: Programming Language :: Python :: 3.11
Classifier: Programming Language :: Python :: 3.12
Classifier: Programming Language :: Python :: Implementation :: CPython
Classifier: License :: OSI Approved :: MIT License
Project-URL: homepage, https://github.com/felinae98/nonebot-bison
Requires-Python: <4.0.0,>=3.10
Requires-Dist: beautifulsoup4>=4.12.3
Requires-Dist: feedparser<7.0.0,>=6.0.11
Requires-Dist: httpx>=0.27.2
Requires-Dist: nonebot2[fastapi]<3.0.0,>=2.3.3
Requires-Dist: nonebot-adapter-onebot<3.0.0,>=2.4.5
Requires-Dist: nonebot-plugin-htmlrender>=0.7.0a1
Requires-Dist: nonebot-plugin-datastore<2.0.0,>=1.3.0
Requires-Dist: nonebot-plugin-apscheduler>=0.5.0
Requires-Dist: nonebot-plugin-send-anything-anywhere<0.7.2,>=0.7.1
Requires-Dist: pillow<11.1,>=11.0.0
Requires-Dist: pyjwt<3.0.0,>=2.9.0
Requires-Dist: python-socketio<6.0.0,>=5.11.4
Requires-Dist: tinydb<5.0.0,>=4.8.0
Requires-Dist: qrcode<8.0.0,>=7.4.2
Requires-Dist: pydantic!=2.5.0,!=2.5.1,<3.0.0,>=2.9.2
Requires-Dist: lxml>=5.3.0
Requires-Dist: yarl>=1.11.1
Requires-Dist: hishel<1.0.0,>=0.0.30
Requires-Dist: expiringdictx<2.0.0,>=1.1.0
Requires-Dist: rapidfuzz<4.0.0,>=3.9.7
Requires-Dist: nonebot-plugin-prometheus>=0.4.1
Provides-Extra: docker
Requires-Dist: nb-cli<2.0.0,>=1.4.2; extra == "docker"
Requires-Dist: nonebot2[aiohttp,fastapi]<3.0.0,>=2.3.3; extra == "docker"
Requires-Dist: nonebot-adapter-qq<2.0.0,>=1.5.1; extra == "docker"
Requires-Dist: nonebot-adapter-satori>=0.13.1; extra == "docker"
Requires-Dist: pip>=24.3.1; extra == "docker"
